quad5/__init__.py
quad5/quadratic_approximation.py
quad5-0.1.14.dist-info/LICENSE
quad5-0.1.14.dist-info/METADATA
quad5-0.1.14.dist-info/WHEEL
quad5-0.1.14.dist-info/top_level.txt
quad5-0.1.14.dist-info/RECORD
