Metadata-Version: 2.1
Name: quad5
Version: 0.1.14
Summary: Quadratic Approximation custom step sampler for PYMC.
Home-page: https://github.com/carsten-j/quad5
Author: Carsten Jørgensen
Author-email: carstenj@gmail.com
License: MIT
Keywords: Bayesian Statistics,Probabalistic Programming Language,Python
Classifier: Programming Language :: Python :: 3
Classifier: License :: OSI Approved :: MIT License
Classifier: Operating System :: OS Independent
License-File: LICENSE
Requires-Dist: PYMC ==5.15.0
